smolyax/__init__.py
smolyax/barycentric.py
smolyax/indices.py
smolyax/interpolation.py
smolyax/nodes/__init__.py
smolyax/nodes/base.py
smolyax/nodes/gausshermite.py
smolyax/nodes/leja.py
smolyax-1.0.0.dist-info/licenses/LICENSE
smolyax-1.0.0.dist-info/METADATA
smolyax-1.0.0.dist-info/WHEEL
smolyax-1.0.0.dist-info/top_level.txt
smolyax-1.0.0.dist-info/RECORD
