Metadata-Version: 2.4
Name: smolyax
Version: 1.0.0
Summary: A high-performance JAX implementation of the Smolyak interpolation operator
Author: Josephine Westermann
Author-email: Joshua Chen <joshuawchen@icloud.com>
License: MIT LICENSE
Requires-Python: >=3.9
License-File: LICENSE
Requires-Dist: jax>=0.4.30
Requires-Dist: numba>=0.60.0
Provides-Extra: cuda
Requires-Dist: jax[cuda]>=0.6.2; extra == "cuda"
Provides-Extra: notebook
Requires-Dist: ipykernel>=6.29.5; extra == "notebook"
Requires-Dist: matplotlib>=3.10.3; extra == "notebook"
Provides-Extra: dev
Requires-Dist: pytest>=8.4.1; extra == "dev"
Requires-Dist: pytest-benchmark>=5.1.0; extra == "dev"
Requires-Dist: pytype; extra == "dev"
Requires-Dist: black>=25.1.0; extra == "dev"
Requires-Dist: flake8>=7.3.0; extra == "dev"
Requires-Dist: flake8-pyproject>=1.2.3; extra == "dev"
Requires-Dist: pdoc>=15.0.4; extra == "dev"
Requires-Dist: mypy>=1.16.1; extra == "dev"
Requires-Dist: ipykernel>=6.29.5; extra == "dev"
Requires-Dist: matplotlib>=3.9.4; extra == "dev"
Dynamic: license-file
